Metadata-Version: 2.1
Name: event-metrics
Version: 0.2.0
Summary: An embedded, event-time metric collection library
Home-page: UNKNOWN
Author: simon-mo
Author-email: xmo@berkeley.edu
License: UNKNOWN
Platform: UNKNOWN
Requires-Python: ==3.*,>=3.5.0
Provides-Extra: dev
